COPYING
COPYING.lesser
MANIFEST.in
NOTICE
README.md
requirements.txt
setup.py
Hikka_Pyro_New.egg-info/PKG-INFO
Hikka_Pyro_New.egg-info/SOURCES.txt
Hikka_Pyro_New.egg-info/dependency_links.txt
Hikka_Pyro_New.egg-info/not-zip-safe
Hikka_Pyro_New.egg-info/requires.txt
Hikka_Pyro_New.egg-info/top_level.txt
compiler/__init__.py
compiler/api/__init__.py
compiler/api/compiler.py
compiler/api/source/auth_key.tl
compiler/api/source/main_api.tl
compiler/api/source/sys_msgs.tl
compiler/api/template/combinator.txt
compiler/api/template/type.txt
compiler/docs/__init__.py
compiler/docs/compiler.py
compiler/docs/template/page.txt
compiler/docs/template/toctree.txt
compiler/errors/__init__.py
compiler/errors/compiler.py
compiler/errors/sort.py
compiler/errors/source/303_SEE_OTHER.tsv
compiler/errors/source/400_BAD_REQUEST.tsv
compiler/errors/source/401_UNAUTHORIZED.tsv
compiler/errors/source/403_FORBIDDEN.tsv
compiler/errors/source/406_NOT_ACCEPTABLE.tsv
compiler/errors/source/420_FLOOD.tsv
compiler/errors/source/500_INTERNAL_SERVER_ERROR.tsv
compiler/errors/source/503_SERVICE_UNAVAILABLE.tsv
compiler/errors/template/class.txt
compiler/errors/template/sub_class.txt
hikkapyro/__init__.py
hikkapyro/client.py
hikkapyro/dispatcher.py
hikkapyro/emoji.py
hikkapyro/file_id.py
hikkapyro/filters.py
hikkapyro/mime_types.py
hikkapyro/py.typed
hikkapyro/sync.py
hikkapyro/utils.py
hikkapyro/connection/__init__.py
hikkapyro/connection/connection.py
hikkapyro/connection/transport/__init__.py
hikkapyro/connection/transport/tcp/__init__.py
hikkapyro/connection/transport/tcp/tcp.py
hikkapyro/connection/transport/tcp/tcp_abridged.py
hikkapyro/connection/transport/tcp/tcp_abridged_o.py
hikkapyro/connection/transport/tcp/tcp_full.py
hikkapyro/connection/transport/tcp/tcp_intermediate.py
hikkapyro/connection/transport/tcp/tcp_intermediate_o.py
hikkapyro/crypto/__init__.py
hikkapyro/crypto/aes.py
hikkapyro/crypto/mtproto.py
hikkapyro/crypto/prime.py
hikkapyro/crypto/rsa.py
hikkapyro/enums/__init__.py
hikkapyro/enums/auto_name.py
hikkapyro/enums/chat_action.py
hikkapyro/enums/chat_event_action.py
hikkapyro/enums/chat_member_status.py
hikkapyro/enums/chat_members_filter.py
hikkapyro/enums/chat_type.py
